dataminds/__init__.py
dataminds/classification.py
dataminds/regression.py
dataminds-0.0.1.dist-info/METADATA
dataminds-0.0.1.dist-info/WHEEL
dataminds-0.0.1.dist-info/top_level.txt
dataminds-0.0.1.dist-info/RECORD
