Metadata-Version: 2.1
Name: dataminds
Version: 0.0.1
Summary: Easily obtain the error metrics related to the problem you are working on
Author: ataozarslan (Ata Ozarslan)
Author-email: <ataozarslan@hotmail.com>
License: UNKNOWN
Keywords: regression,classification,model evaluation,error metrics
Platform: UNKNOWN
Requires-Dist: pandas
Requires-Dist: sklearn
